.VERSION
AUTHORS.rst
CONTRIBUTING.rst
HISTORY.rst
LICENSE
MANIFEST.in
Pipfile
Pipfile.lock
README.rst
USAGE.rst
dev-requirements.txt
requirements.txt
setup.cfg
setup.py
docs/Makefile
docs/authors.rst
docs/conf.py
docs/contributing.rst
docs/history.rst
docs/index.rst
docs/installation.rst
docs/readme.rst
docs/usage.rst
opsgenielib/.VERSION
opsgenielib/AUTHORS.rst
opsgenielib/CONTRIBUTING.rst
opsgenielib/HISTORY.rst
opsgenielib/LICENSE
opsgenielib/Pipfile
opsgenielib/Pipfile.lock
opsgenielib/README.rst
opsgenielib/USAGE.rst
opsgenielib/__init__.py
opsgenielib/_version.py
opsgenielib/dev-requirements.txt
opsgenielib/opsgenielib.py
opsgenielib/opsgenielibexceptions.py
opsgenielib/requirements.txt
opsgenielib.egg-info/PKG-INFO
opsgenielib.egg-info/SOURCES.txt
opsgenielib.egg-info/dependency_links.txt
opsgenielib.egg-info/not-zip-safe
opsgenielib.egg-info/requires.txt
opsgenielib.egg-info/top_level.txt
opsgenielib/__pycache__/__init__.cpython-310.pyc
opsgenielib/__pycache__/__init__.cpython-39.pyc
opsgenielib/__pycache__/_version.cpython-310.pyc
opsgenielib/__pycache__/_version.cpython-39.pyc
opsgenielib/__pycache__/opsgenielib.cpython-310.pyc
opsgenielib/__pycache__/opsgenielib.cpython-39.pyc
opsgenielib/__pycache__/opsgenielibexceptions.cpython-310.pyc
opsgenielib/__pycache__/opsgenielibexceptions.cpython-39.pyc
tests/test_opsgenielib.py