Metadata-Version: 2.1
Name: opsgenielib
Version: 0.0.46
Summary: A python library for Opsgenie
Home-page: https://sbp.gitlab.schubergphilis.com/SaaS/opsgenielib
Author: Yorick Hoorneman
Author-email: yhoorneman@schubergphilis.com
License: MIT
Keywords: opsgenielib
Classifier: Development Status :: 5 - Production/Stable
Classifier: Intended Audience :: Developers
Classifier: License :: OSI Approved :: MIT License
Classifier: Natural Language :: English
Classifier: Programming Language :: Python :: 3.7
License-File: LICENSE
License-File: AUTHORS.rst
Requires-Dist: requests~=2.32.3; python_version >= "3.8"
Requires-Dist: pytz~=2024.2
Requires-Dist: semver==2.13.0; python_version >= "2.7" and python_version not in "3.0, 3.1, 3.2, 3.3"
Requires-Dist: python-dateutil~=2.9.0.post0; python_version >= "2.7" and python_version not in "3.0, 3.1, 3.2, 3.3"
Requires-Dist: twine~=5.1.1; python_version >= "3.8"
